primify/__init__.py
primify/base.py
primify/cli.py
primify/prime_finder.py
primify-2.0.0.dist-info/AUTHORS.rst
primify-2.0.0.dist-info/LICENSE.txt
primify-2.0.0.dist-info/METADATA
primify-2.0.0.dist-info/WHEEL
primify-2.0.0.dist-info/entry_points.txt
primify-2.0.0.dist-info/top_level.txt
primify-2.0.0.dist-info/RECORD
