Metadata-Version: 2.1
Name: primify
Version: 2.0.0
Summary: Embed any image into a prime number.
Home-page: https://github.com/LeviBorodenko/primify
Author: Levi Borodenko
Author-email: Levi.borodenko@gmail.com
License: mit
Project-URL: Documentation, https://github.com/LeviBorodenko/primify
Platform: any
Classifier: Development Status :: 4 - Beta
Classifier: Programming Language :: Python
Requires-Python: >=3.8
License-File: LICENSE.txt
License-File: AUTHORS.rst
Requires-Dist: certifi (==2019.3.9)
Requires-Dist: mpmath (==1.1.0)
Requires-Dist: Pillow (==8.4.0)
Requires-Dist: sympy (==1.9)
Requires-Dist: gmpy2 (==2.1.1)
Requires-Dist: rich (==10.16.1)
Provides-Extra: testing
Requires-Dist: pytest ; extra == 'testing'
Requires-Dist: pytest-cov ; extra == 'testing'
